pcg_skel/__init__.py
pcg_skel/chunk_cache.py
pcg_skel/chunk_tools.py
pcg_skel/features.py
pcg_skel/nocache.py
pcg_skel/pcg_anno.py
pcg_skel/pcg_skel.py
pcg_skel/service.py
pcg_skel/skel_utils.py
pcg_skel/utils.py
pcg_skel-1.3.1.dist-info/METADATA
pcg_skel-1.3.1.dist-info/WHEEL
pcg_skel-1.3.1.dist-info/licenses/LICENSE
pcg_skel-1.3.1.dist-info/RECORD
