Metadata-Version: 2.4
Name: pcg-skel
Version: 1.3.1
Summary: Skeletonization using the pychunkedgraph
Project-URL: Repository, https://github.com/AllenInstitute/pcg_skel
Author-email: Casey Schneider-mizell <caseys@alleninstitute.org>
Maintainer-email: Casey Schneider-mizell <caseys@alleninstitute.org>
License: MIT License
License-File: LICENSE
Requires-Python: >=3.9
Requires-Dist: caveclient>=6.4.1
Requires-Dist: cloud-volume>=11.1.3
Requires-Dist: fastremap
Requires-Dist: meshparty>=1.12.0
Requires-Dist: numpy
Requires-Dist: orjson
Requires-Dist: pandas
Requires-Dist: scipy
Requires-Dist: sqlitedict
Requires-Dist: trimesh
